ode_explorer/__init__.py
ode_explorer/constants.py
ode_explorer/defaults.py
ode_explorer/types.py
ode_explorer/version.py
ode_explorer/callbacks/__init__.py
ode_explorer/callbacks/callback.py
ode_explorer/examples/__init__.py
ode_explorer/integrators/__init__.py
ode_explorer/integrators/integrator.py
ode_explorer/integrators/integrator_loops.py
ode_explorer/integrators/loop_factory.py
ode_explorer/metrics/__init__.py
ode_explorer/metrics/metric.py
ode_explorer/models/__init__.py
ode_explorer/models/base_model.py
ode_explorer/models/hamiltonian_system.py
ode_explorer/models/messages.py
ode_explorer/models/model.py
ode_explorer/stepfunctions/__init__.py
ode_explorer/stepfunctions/stepfunctions.py
ode_explorer/stepfunctions/stepfunctions_impl.py
ode_explorer/stepfunctions/templates.py
ode_explorer/stepsize_control/__init__.py
ode_explorer/stepsize_control/stepsizecontroller.py
ode_explorer/testing/__init__.py
ode_explorer/testing/cython_speedtest.py
ode_explorer/testing/hamiltonian_system_test.py
ode_explorer/testing/integrator_test.py
ode_explorer/testing/io_test.py
ode_explorer/testing/rk_template_test.py
ode_explorer/utils/__init__.py
ode_explorer/utils/data_utils.py
ode_explorer/utils/helpers.py
ode_explorer/utils/import_utils.py
ode_explorer/utils/run_utils.py
ode_explorer-0.0.1a2.dist-info/LICENSE
ode_explorer-0.0.1a2.dist-info/METADATA
ode_explorer-0.0.1a2.dist-info/WHEEL
ode_explorer-0.0.1a2.dist-info/top_level.txt
ode_explorer-0.0.1a2.dist-info/RECORD
